certbot_dns_rackspace/__init__.py
certbot_dns_rackspace-0.0.1.dev2.dist-info/LICENSE
certbot_dns_rackspace-0.0.1.dev2.dist-info/METADATA
certbot_dns_rackspace-0.0.1.dev2.dist-info/WHEEL
certbot_dns_rackspace-0.0.1.dev2.dist-info/entry_points.txt
certbot_dns_rackspace-0.0.1.dev2.dist-info/top_level.txt
certbot_dns_rackspace-0.0.1.dev2.dist-info/RECORD
